LICENSE
MANIFEST.in
README.rst
pyesdoc.conf
requirements.txt
runtests.sh
setup.cfg
setup.py
pyesdoc/__init__.py
pyesdoc/_api_proxy.py
pyesdoc/_associating.py
pyesdoc/_factory.py
pyesdoc/_io.py
pyesdoc/_publishing.py
pyesdoc/_search.py
pyesdoc/_security.py
pyesdoc/_serialization.py
pyesdoc/_validation.py
pyesdoc/constants.py
pyesdoc/exceptions.py
pyesdoc.egg-info/PKG-INFO
pyesdoc.egg-info/SOURCES.txt
pyesdoc.egg-info/dependency_links.txt
pyesdoc.egg-info/not-zip-safe
pyesdoc.egg-info/requires.txt
pyesdoc.egg-info/top_level.txt
pyesdoc/_codecs/__init__.py
pyesdoc/_codecs/dictionary/__init__.py
pyesdoc/_codecs/dictionary/decoder.py
pyesdoc/_codecs/dictionary/encoder.py
pyesdoc/_codecs/html/__init__.py
pyesdoc/_codecs/html/decoder.py
pyesdoc/_codecs/html/encoder.py
pyesdoc/_codecs/html/fieldsets/__init__.py
pyesdoc/_codecs/html/fieldsets/cim_1.py
pyesdoc/_codecs/html/fieldsets/cim_2.py
pyesdoc/_codecs/html/fieldsets/factory.py
pyesdoc/_codecs/html/fieldsets/field.py
pyesdoc/_codecs/html/templates/__init__.py
pyesdoc/_codecs/html/templates/cim_1/activity_ensemble.html
pyesdoc/_codecs/html/templates/cim_1/activity_ensemble_member.html
pyesdoc/_codecs/html/templates/cim_1/activity_ensemble_members.html
pyesdoc/_codecs/html/templates/cim_1/activity_ensemble_overview.html
pyesdoc/_codecs/html/templates/cim_1/activity_numerical_experiment.html
pyesdoc/_codecs/html/templates/cim_1/activity_numerical_experiment_requirements.html
pyesdoc/_codecs/html/templates/cim_1/activity_numerical_requirement.html
pyesdoc/_codecs/html/templates/cim_1/activity_simulation_run.html
pyesdoc/_codecs/html/templates/cim_1/activity_simulation_run_details.html
pyesdoc/_codecs/html/templates/cim_1/activity_simulation_run_input.html
pyesdoc/_codecs/html/templates/cim_1/activity_simulation_run_inputs.html
pyesdoc/_codecs/html/templates/cim_1/activity_simulation_run_model_mods.html
pyesdoc/_codecs/html/templates/cim_1/data_data_object.html
pyesdoc/_codecs/html/templates/cim_1/data_data_object_overview.html
pyesdoc/_codecs/html/templates/cim_1/grids_grid_mosaic.html
pyesdoc/_codecs/html/templates/cim_1/grids_grid_spec.html
pyesdoc/_codecs/html/templates/cim_1/grids_grid_tile.html
