Metadata-Version: 1.1
Name: pyesdoc
Version: 0.15.0.0
Summary: pyesdoc is a python library for publishing earth system documentation.
Home-page: https://github.com/ES-DOC/esdoc-py-client
Author: Mark A. Greenslade
Author-email: momipsl@ipsl.jussieu.fr
License: GPL/CeCILL-2.1
Platform: UNKNOWN
Classifier: Development Status :: 4 - Beta
Classifier: Intended Audience :: Developers
Classifier: Natural Language :: English
Classifier: License :: OSI Approved :: GNU General Public License (GPL)
Classifier: License :: OSI Approved :: CEA CNRS Inria Logiciel Libre License, version 2.1 (CeCILL-2.1)
Classifier: Operating System :: OS Independent
Classifier: Programming Language :: Python
Classifier: Programming Language :: Python :: 2
Classifier: Programming Language :: Python :: 2.7
Classifier: Topic :: Software Development :: Libraries :: Python Modules
